errorcollector/__init__.py
errorcollector/error_collector.py
errorcollector/py.typed
errorcollector-1.0.1.dist-info/licenses/LICENSE
errorcollector-1.0.1.dist-info/METADATA
errorcollector-1.0.1.dist-info/WHEEL
errorcollector-1.0.1.dist-info/top_level.txt
errorcollector-1.0.1.dist-info/RECORD
